labby/__init__.py
labby/commands/build.py
labby/commands/common.py
labby/commands/configuration.py
labby/commands/connect.py
labby/commands/create.py
labby/commands/delete.py
labby/commands/get.py
labby/commands/restart.py
labby/commands/run.py
labby/commands/start.py
labby/commands/stop.py
labby/commands/update.py
labby/config.py
labby/main.py
labby/models.py
labby/nornir/__init__.py
labby/nornir/plugins/__init__.py
labby/nornir/plugins/inventory/__init__.py
labby/nornir/plugins/inventory/labby.py
labby/nornir_tasks.py
labby/project_data.py
labby/providers/__init__.py
labby/providers/gns3/__init__.py
labby/providers/gns3/console_provisioner.py
labby/providers/gns3/link.py
labby/providers/gns3/node.py
labby/providers/gns3/project.py
labby/providers/gns3/provider.py
labby/providers/gns3/template.py
labby/providers/gns3/utils.py
labby/state_file.py
labby/templates/base_config.toml.j2
labby/templates/nodes_bootstrap/arista_eos.cfg.j2
labby/templates/nodes_bootstrap/cisco_ios.cfg.j2
labby/templates/nodes_bootstrap/cisco_nxos.cfg.j2
labby/utils.py
labby-0.2.0.dist-info/entry_points.txt
labby-0.2.0.dist-info/WHEEL
labby-0.2.0.dist-info/METADATA
labby-0.2.0.dist-info/RECORD
