Metadata-Version: 2.1
Name: labby
Version: 0.2.0
Summary: CLI tool to build Network Labs in an automated way
Home-page: https://github.com/davidban77/labby
License: MIT
Keywords: network,gns3,python,cli
Author: David Flores
Author-email: davidflores7_8@hotmail.com
Requires-Python: >=3.7,<4.0
Classifier: License :: OSI Approved :: MIT License
Classifier: Programming Language :: Python :: 3
Classifier: Programming Language :: Python :: 3.10
Classifier: Programming Language :: Python :: 3.7
Classifier: Programming Language :: Python :: 3.8
Classifier: Programming Language :: Python :: 3.9
Requires-Dist: Jinja2 (>=3.1.2,<4.0.0)
Requires-Dist: PyYAML (>=6.0,<7.0)
Requires-Dist: gns3fy (>=1.0.0rc1)
Requires-Dist: netaddr (>=0.8.0,<0.9.0)
Requires-Dist: nornir (>=3.3.0,<4.0.0)
Requires-Dist: nornir-scrapli (==2020.11.1)
Requires-Dist: pydantic[dotenv] (>=1.9.1,<2.0.0)
Requires-Dist: rich (>=12.4.1,<13.0.0)
Requires-Dist: scrapli (==2020.10.10)
Requires-Dist: toml (>=0.10.2,<0.11.0)
Requires-Dist: typer (>=0.4.1,<0.5.0)
Project-URL: Repository, https://github.com/davidban77/labby
